setup.py
dsnd_probability_2020_15/Binomialdistribution.py
dsnd_probability_2020_15/Gaussiandistribution.py
dsnd_probability_2020_15/Generaldistribution.py
dsnd_probability_2020_15/__init__.py
dsnd_probability_2020_15.egg-info/PKG-INFO
dsnd_probability_2020_15.egg-info/SOURCES.txt
dsnd_probability_2020_15.egg-info/dependency_links.txt
dsnd_probability_2020_15.egg-info/not-zip-safe
dsnd_probability_2020_15.egg-info/top_level.txt