Metadata-Version: 1.0
Name: dsnd-probability-2020-15
Version: 1.0
Summary: Gaussian and Binomial distributions
Home-page: UNKNOWN
Author: Ogundeyi Boluwatife
Author-email: tifeasypeasy@gmail.com
License: UNKNOWN
Platform: UNKNOWN
